icbs/__init__.py
icbs/cut.py
icbs/rebuild.py
icbs-0.0.2.dist-info/LICENSE
icbs-0.0.2.dist-info/METADATA
icbs-0.0.2.dist-info/WHEEL
icbs-0.0.2.dist-info/top_level.txt
icbs-0.0.2.dist-info/RECORD
