Metadata-Version: 2.1
Name: icbs
Version: 0.0.2
Summary: Simple image cut and rebuild package. It allows to decide how to cut an image in overlapping squares. After having cut the image you can rebuild it (or you can do some processing before rebuilding it)
Home-page: https://github.com/lolloz98/icbs
Author: Lorenzo Carpaneto
License: UNKNOWN
Platform: UNKNOWN
Classifier: Programming Language :: Python :: 3
Classifier: License :: OSI Approved :: MIT License
Classifier: Operating System :: OS Independent
Requires-Python: >=3.6
Requires-Dist: numpy
